ppp/__init__.py
ppp/cli.py
ppp/toml_service.py
ppp/toml_service_test.py
ppp/tests/__init__.py
ppp/tests/lib.py
ppp_run-0.2.1.dist-info/METADATA
ppp_run-0.2.1.dist-info/WHEEL
ppp_run-0.2.1.dist-info/entry_points.txt
ppp_run-0.2.1.dist-info/top_level.txt
ppp_run-0.2.1.dist-info/RECORD
